Metadata-Version: 1.0
Name: sulla
Version: 0.1
Summary: Property-based testing for Webots
Home-page: https://github.com/demiourgoi/sulla
Author: Juan Rodriguez Hortala
Author-email: juan.rodriguez.hortala@gmail.com
License: Apache 2.0
Platform: UNKNOWN
